[
  {
    "id": "shtukaturka",
    "categories": [
      {
        "id": 1,
        "categoryTitle": "Штукатурка гіпсова",
        "isCategoryOpen": true,
        "materials": [
          {
            "id": 1.1,
            "image": "https://i.imgur.com/eNFaG10.jpeg",
            "title": "Knauf MP75",
            "description": "Knauf MP 75, штукатурка гіпсова машинного нанесення застосовується для штукатурення різних мінеральних поверхонь, як правило, машинним способом. У кінцевому результаті отримаємо міцний шар, який в подальшому може бути оброблений декоративною штукатуркою або цементної шпаклівкою.",
            "weight": 30,
            "price": 297.9,
            "quantity": 0,
            "totalPrice": 0
          }
        ]
      },
      {
        "id": 2,
        "categoryTitle": "Штукатурка цементна",
        "isCategoryOpen": false,
        "materials": [
          {
            "id": 2.1,
            "image": "https://i.imgur.com/3DOs18B.jpeg",
            "title": "Siltek PM-10 цементно-вапняна",
            "description": "Для вирівнювання недеформівних бетонних, цементно-вапняних, цементно-піщаних та гіпсових поверхонь (стін і стель) шаром до 50 мм всередині житлових приміщень, які не підпадають під систематичне зволоження, перед шпаклівкою.",
            "weight": 25,
            "price": 120.6,
            "quantity": 0,
            "totalPrice": 0
          },
          {
            "id": 2.2,
            "image": "https://i.imgur.com/Bb2lO1B.jpeg",
            "title": "Baumit MPI 25",
            "description": "Цементно-вапняна суміш з мінеральними заповнювачами та полімерними добавками.  Призначена для механізованого штукатурення всіх видів щільних мінеральних основ всередині будівель. Придатна для нанесення",
            "weight": 25,
            "price": 120.74,
            "quantity": 0,
            "totalPrice": 0
          },
          {
            "id": 2.3,
            "image": "https://i.imgur.com/uityeHs.jpg",
            "title": "Polimin (Полимин) ШВ-1 ",
            "description": "Застосовується для виконання високоякісних штукатурних робіт на різних мінеральних основах (бетон, цегла і т.д.) усередині приміщень. Рекомендована як для традиційного ручного, так і для механічного нанесення. Після затвердіння є міцною основою для гіпсових шпаклівок і внутрішніх декоративних штукатурок.",
            "weight": 25,
            "price": 125.96,
            "quantity": 0,
            "totalPrice": 0
          }
        ]
      },
      {
        "id": 3,
        "categoryTitle": "Маяк штукатурний",
        "isCategoryOpen": false,
        "materials": [
          {
            "id": 3.1,
            "image": "https://i.imgur.com/PAvMJqJ.jpeg",
            "title": "Маяк  штукатурний  6 мм (0,25) 3м ",
            "description": "При виробництві штукатурних робіт для полегшення вирівнювання поверхонь використовують металеві маяки з Т-образним профілем. Маяк штукатурний виготовляється з металевої стрічки холоднопрокатної методом.",
            "weight": 0.2,
            "price": 15.3,
            "quantity": 0,
            "totalPrice": 0
          },
          {
            "id": 3.2,
            "image": "https://i.imgur.com/PAvMJqJ.jpeg",
            "title": "Маяк  штукатурний  6 мм (0,30) 3м ",
            "description": "При виробництві штукатурних робіт для полегшення вирівнювання поверхонь використовують металеві маяки з Т-образним профілем. Маяк штукатурний виготовляється з металевої стрічки холоднопрокатної методом.",
            "weight": 0.2,
            "price": 17.08,
            "quantity": 0,
            "totalPrice": 0
          },
          {
            "id": 3.3,
            "image": "https://i.imgur.com/PAvMJqJ.jpeg",
            "title": "Маяк  штукатурний  6 мм (0,35) 3м ",
            "description": "При виробництві штукатурних робіт для полегшення вирівнювання поверхонь використовують металеві маяки з Т-образним профілем. Маяк штукатурний виготовляється з металевої стрічки холоднопрокатної методом.",
            "weight": 0.2,
            "price": 20.7,
            "quantity": 0,
            "totalPrice": 0
          },
          {
            "id": 3.4,
            "image": "https://i.imgur.com/PAvMJqJ.jpeg",
            "title": "Маяк  штукатурний  10 мм (0,3) 3м ",
            "description": "При виробництві штукатурних робіт для полегшення вирівнювання поверхонь використовують металеві маяки з Т-образним профілем. Маяк штукатурний виготовляється з металевої стрічки холоднопрокатної методом.",
            "weight": 0.2,
            "price": 24.84,
            "quantity": 0,
            "totalPrice": 0
          },
          {
            "id": 3.5,
            "image": "https://i.imgur.com/PAvMJqJ.jpeg",
            "title": "Маяк  штукатурний  10 мм (0,35) 3м ",
            "description": "При виробництві штукатурних робіт для полегшення вирівнювання поверхонь використовують металеві маяки з Т-образним профілем. Маяк штукатурний виготовляється з металевої стрічки холоднопрокатної методом.",
            "weight": 0.2,
            "price": 27.26,
            "quantity": 0,
            "totalPrice": 0
          }
        ]
      },
      {
        "id": 4,
        "categoryTitle": "Бетоноконтакт",
        "isCategoryOpen": false,
        "materials": [
          {
            "id": 4.1,
            "image": "https://i.imgur.com/B8o6tYi.jpeg",
            "title": "KNAUF Грунт БЕТОКОНТАКТ, 5 кг ",
            "description": "Грунтовка Бетоконтакт призначена для попередньої обробки під гіпсову штукатурку щільних, гладких, слабо і не всмоктують вологу поверхонь: монолітного бетону, масивних бетонних стель використовується для внутрішніх робіт. Також можуть оброблятися обшивки з гіпсокартону і поверхні пінополістирольних плит.",
            "weight": 5,
            "price": 361.31,
            "quantity": 0,
            "totalPrice": 0
          },
          {
            "id": 4.2,
            "image": "https://i.imgur.com/ZB9ddKW.jpeg",
            "title": "KNAUF Грунт БЕТОКОНТАКТ, 20 кг ",
            "description": "Грунтовка Бетоконтакт призначена для попередньої обробки під гіпсову штукатурку щільних, гладких, слабо і не всмоктують вологу поверхонь: монолітного бетону, масивних бетонних стель використовується для внутрішніх робіт. Також можуть оброблятися обшивки з гіпсокартону і поверхні пінополістирольних плит.",
            "weight": 20,
            "price": 1381.91,
            "quantity": 0,
            "totalPrice": 0
          }
        ]
      },
      {
        "id": 5,
        "categoryTitle": "Грунтовка",
        "isCategoryOpen": false,
        "materials": [
          {
            "id": 5.1,
            "image": "https://i.imgur.com/xJ16Teg.jpeg",
            "title": "KNAUF Грунт ГРУНДІРМІТЕЛЬ, 10 кг УКРАІНА ",
            "description": "Knauf Грундірміттель - грунтовка, що застосовується для обробки гідроскопічністю підстав для забезпечення рівномірного схоплювання гіпсового штукатурного розчину при подальшому оштукатурюванні. Використовується також для поліпшення зчеплення з поверхнею з газо- і пінобетону, силікатної та керамічної цегли.",
            "weight": 10,
            "price": 771.44,
            "quantity": 0,
            "totalPrice": 0
          },
          {
            "id": 5.2,
            "image": "https://i.imgur.com/wdxOTll.jpeg",
            "title": "  SILTEK Е-100/10л Ґрунтівка Universal (універсальна)",
            "description": "Грунтовка Siltek Е-100 призначена для зміцнення та просочування поглинаючих основ перед нанесенням дисперсійних фарб для зменшення їх витрати, клейових розчинів, фінішних шпаклівок, приклеюванням керамічної плитки та шпалер, нанесенням основи для покриттів для підлоги.",
            "weight": 10,
            "price": 307.2,
            "quantity": 0,
            "totalPrice": 0
          },
          {
            "id": 5.3,
            "image": "https://i.imgur.com/2ZycTgo.jpeg",
            "title": "CERESIT Грунт СТ-17, 10 літрів ",
            "description": "Ґрунтівка глибокопроникна Ceresit СТ 17 призначена для підготовки (зниження та вирівнювання водопоглинання, знепилення, укріплення) зовнішніх та внутрішніх мінеральних поверхонь перед виконанням опоряджувальних робіт...",
            "weight": 10,
            "price": 385.97,
            "quantity": 0,
            "totalPrice": 0
          },
          {
            "id": 5.4,
            "image": "https://i.imgur.com/XjbPMTw.jpeg",
            "title": "Artisan №7 глибокопроникла 10 л ",
            "description": "Ґрунт ARTISAN №7 Universal застосовують для підготовки будь-яких мінеральних поверхонь з бетону, цегли, піно- і газобетону, гіпсокартону, цементної штукатурки, азбестоцементу, перед оштукатурюванням, шпаклюванням, фарбуванням, наклеюванням керамічної плитки, а також для ґрунтування підлог перед нанесенням самовирівнюючих сумішей, укладанням оздоблювальних підлогових матеріалів, зовні і всередині приміщень.",
            "weight": 10,
            "price": 232.78,
            "quantity": 0,
            "totalPrice": 0
          }
        ]
      },
      {
        "id": 6,
        "categoryTitle": "Кутник пластиковий",
        "isCategoryOpen": false,
        "materials": [
          {
            "id": 6.1,
            "image": "https://i.imgur.com/wjrHbuP.jpeg",
            "title": "Кутник ПЛАСТИКОВИЙ ПЛЕТІНКА для мокрої штукатурки 3м ",
            "description": "Кутник ПВХ для мокрої штукатурки призначений для формування, вирівнювання і захисту від ушкоджень зовнішньої поверхні кута під час виконання штукатурення «мокрим способом» на внутрішніх чи зовнішніх стінах",
            "weight": 0.1,
            "price": 21.44,
            "quantity": 0,
            "totalPrice": 0
          },
          {
            "id": 6.2,
            "image": "https://i.imgur.com/EQv2diX.jpeg",
            "title": "Профіль кутовий ПЕРФОРОВАНИЙ ПЛАСТИКОВИЙ малярний, 3м",
            "description": "Пластикові Перфоровані кути призначені для додання міцності і довговічності зовнішнім прямим і арочним кутах при внутрішній обробці приміщень матеріалами типу гіпсокартон, а так само при проведенні штукатурних робіт, обробці вікон, фарбування стін і т.д.",
            "weight": 0.1,
            "price": 10.47,
            "quantity": 0,
            "totalPrice": 0
          }
        ]
      },
      {
        "id": 7,
        "categoryTitle": "Профіль привіконний",
        "isCategoryOpen": false,
        "materials": [
          {
            "id": 7.1,
            "image": "https://i.imgur.com/VSek0uV.jpeg",
            "title": "Профіль віконий примикаючий 2.4м 6/3мм ",
            "description": "Профіль віконний прилеглий ПВХ призначений для якісного формування віконних і дверних відкосів. Перевагою є стійкість до ультрафіолету й повний захист монтажного шва від погодних умов завдяки наявному ущільнювачу. Кут-профіль віконний використовується як у середині, так і назовні фасадів будівель для захисту вікон або дверей під час виконання оздоблювальних робіт.",
            "weight": 0.1,
            "price": 46.37,
            "quantity": 0,
            "totalPrice": 0
          },
          {
            "id": 7.2,
            "image": "https://i.imgur.com/kVE1ASw.jpeg",
            "title": "Профіль віконий примикаючий з СІТКОЮ 2.5м 6/3мм",
            "description": "Профіль віконний прилеглий ПВХ призначений для якісного формування віконних і дверних відкосів. Перевагою є стійкість до ультрафіолету й повний захист монтажного шва від погодних умов завдяки наявному ущільнювачу. Кут-профіль віконний використовується як у середині, так і назовні фасадів будівель для захисту вікон або дверей під час виконання оздоблювальних робіт.",
            "weight": 0.1,
            "price": 80.5,
            "quantity": 0,
            "totalPrice": 0
          }
        ]
      },
      {
        "id": 8,
        "categoryTitle": "Сітка штукатурна армуюча (скловолокно)",
        "isCategoryOpen": false,
        "materials": [
          {
            "id": 8.1,
            "image": "https://i.imgur.com/bijPpG4.jpeg",
            "title": "Штукатурна сітка 145 г/м2 WORKS Синя, 5ммх5мм, рулон 1м*50м",
            "description": "Застосовується для армування поверхні, захисту поверхні від тріщин, гідроізоляції будівель, внутрішній обробки різних споруд. Висока опірність до розривів і розтягувань. Висока стійкість до впливу лужних розчинів. Запобігає утворенню тріщин в штукатурному шарі.",
            "weight": 0.5,
            "price": 482.49,
            "quantity": 0,
            "totalPrice": 0
          },
          {
            "id": 8.2,
            "image": "https://i.imgur.com/XSDCXY2.jpeg",
            "title": "  Штукатурна сітка 160 г/м2 WORKS PRO ПОМАРАНЧЕВА, 5ммх5мм, рулон 1м*50м ",
            "description": "Застосовується для армування поверхні, захисту поверхні від тріщин, гідроізоляції будівель, внутрішній обробки різних споруд. Висока опірність до розривів і розтягувань. Висока стійкість до впливу лужних розчинів. Запобігає утворенню тріщин в штукатурному шарі.",
            "weight": 0.5,
            "price": 535.8,
            "quantity": 0,
            "totalPrice": 0
          }
        ]
      },
      {
        "id": 9,
        "categoryTitle": "Плівка захисна",
        "isCategoryOpen": false,
        "materials": [
          {
            "id": 9.1,
            "image": "https://i.imgur.com/AURAd9R.jpeg",
            "title": "Плівка захисна малярська 4х5м, 20мкр",
            "description": "Плівка захисна призначена для захисту меблів, підлоги, стін від забруднення при виконанні ремонтних робіт. Захисна плівка призначена для застосування всередині приміщень",
            "weight": 0.5,
            "price": 40,
            "quantity": 0,
            "totalPrice": 0
          },
          {
            "id": 9.2,
            "image": "https://i.imgur.com/BE1HWZi.jpeg",
            "title": "Плівка п/ет  80мк, 1,5м*100м.п*2 рукав, 300м.кв",
            "description": "Застосовується для армування поверхні, захисту поверхні від тріщин, гідроізоляції будівель, внутрішній обробки різних споруд. Висока опірність до розривів і розтягувань. Висока стійкість до впливу лужних розчинів. Запобігає утворенню тріщин в штукатурному шарі.",
            "weight": 0.5,
            "price": 1089,
            "quantity": 0,
            "totalPrice": 0
          }
        ]
      },
      {
        "id": 10,
        "categoryTitle": "Стрічка малярна",
        "isCategoryOpen": false,
        "materials": [
          {
            "id": 10.1,
            "image": "https://i.imgur.com/pApmMAN.jpeg",
            "title": "Стрічка  малярська 48 мм, рулон 20 м Eskaro",
            "description": "Клейка малярська стрічка використовується для збереження чистоти поверхонь, обмеження зон фарбування, захисту поверхонь від фарби у випадках неможливості демонтажу знімних елементів конструкції",
            "weight": 0.1,
            "price": 42.68,
            "quantity": 0,
            "totalPrice": 0
          },
          {
            "id": 10.2,
            "image": "https://i.imgur.com/pApmMAN.jpeg",
            "title": "Стрічка  малярська 48 мм, рулон 40 м Eskaro",
            "description": "Клейка малярська стрічка використовується для збереження чистоти поверхонь, обмеження зон фарбування, захисту поверхонь від фарби у випадках неможливості демонтажу знімних елементів конструкції",
            "weight": 0.1,
            "price": 76.4,
            "quantity": 0,
            "totalPrice": 0
          }
        ]
      },
      {
        "id": 11,
        "categoryTitle": "Супутні матеріали",
        "isCategoryOpen": false,
        "materials": [
          {
            "id": 11.1,
            "image": "https://i.imgur.com/HBCDOjK.jpeg",
            "title": " Правило трапецевидне 300 см арт. 0730-523000 ХАРДЕКС",
            "description": "правило використовується при штукатурних роботах для швидкого та ефективного розподілу розчину по оброблюваної поверхні, а також для вирівнювання штукатурних шарів у вертикальному та горизонтальному положеннях",
            "weight": 2,
            "price": 1131.58,
            "quantity": 0,
            "totalPrice": 0
          },
          {
            "id": 11.2,
            "image": "https://i.imgur.com/xZqqESt.jpeg",
            "title": "Мішки для сміття П/П 55смХ 90см",
            "description": "Універсальність і зручність. Формат поліпропіленового мішка  дозволяє підібрати оптимальний варіант для будь-яких потреб. Ви можете використовувати його для пакування піску, цементу, зерна, корму, насіння, соломи, будматеріалів і багатьох інших речей",
            "weight": 0.1,
            "price": 6.08,
            "quantity": 0,
            "totalPrice": 0
          },
          {
            "id": 11.3,
            "image": "https://i.imgur.com/xp6Blcl.jpeg",
            "title": "Рукавички  з покриттям ПВХ крапка",
            "description": "Спеціальний малюнок у вигляді ПВХ-покриття забезпечує надійність захоплення в процесі роботи і дозволяє зберігати максимальний контроль над інструментами і матеріалами, що оброблюються. Рукавички мають оптимальну жорсткість, яка дає можливість легко і точно виконувати роботи з невеликими деталями та інструментами.",
            "weight": 0.1,
            "price": 15.63,
            "quantity": 0,
            "totalPrice": 0
          },
          {
            "id": 11.4,
            "image": "https://i.imgur.com/x3GwTGs.jpeg",
            "title": "Відро Будівельне  20 л. (Польща)",
            "description": "Пластикові відра можуть використовуватися для змішування різних матеріалів, таких як цемент та пісок, для створення бетонної суміші. Це швидкий та ефективний спосіб змішування матеріалів без необхідності використання інших інструментів.",
            "weight": 0.2,
            "price": 78.75,
            "quantity": 0,
            "totalPrice": 0
          },
          {
            "id": 11.5,
            "image": "https://i.imgur.com/HgII2Yb.jpeg",
            "title": "Кастра кругла 65 л. (Польща)",
            "description": "Пластикові відра можуть використовуватися для змішування різних матеріалів, таких як цемент та пісок, для створення бетонної суміші. Це швидкий та ефективний спосіб змішування матеріалів без необхідності використання інших інструментів.",
            "weight": 0.2,
            "price": 207.5,
            "quantity": 0,
            "totalPrice": 0
          }
        ]
      }
    ]
  },
  {
    "id": "gipsokarton",
    "categories": [
      {
        "id": 12,
        "categoryTitle": "Гіпсокартон стіновий (вологостікий)",
        "isCategoryOpen": true,
        "materials": [
          {
            "id": 12.1,
            "image": "https://i.imgur.com/qFCxJEB.jpeg",
            "title": "Knauf 2000х1200х12.5 мм",
            "description": "",
            "weight": 20,
            "price": 287.66,
            "quantity": 0,
            "totalPrice": 0
          },
          {
            "id": 12.2,
            "image": "https://i.imgur.com/qFCxJEB.jpeg",
            "title": "Knauf 2500х1200х12.5 мм",
            "description": "",
            "weight": 30,
            "price": 359.58,
            "quantity": 0,
            "totalPrice": 0
          },
          {
            "id": 12.3,
            "image": "https://i.imgur.com/qFCxJEB.jpeg",
            "title": "Knauf 3000х1200х12.5 мм",
            "description": "",
            "weight": 25,
            "price": 431.5,
            "quantity": 0,
            "totalPrice": 0
          }
        ]
      },
      {
        "id": 13,
        "categoryTitle": "Гіпсокартон стіновий (звичайний)",
        "isCategoryOpen": false,
        "materials": [
          {
            "id": 13.1,
            "image": "https://i.imgur.com/EoCn52n.jpeg",
            "title": "Knauf 2000х1200х12.5 мм",
            "description": "",
            "weight": 25,
            "price": 239.86,
            "quantity": 0,
            "totalPrice": 0
          },
          {
            "id": 13.2,
            "image": "https://i.imgur.com/EoCn52n.jpeg",
            "title": "Knauf 2500х1200х12.5 мм",
            "description": "Цементно-вапняна суміш з мінеральними заповнювачами та полімерними добавками.  Призначена для механізованого штукатурення всіх видів щільних мінеральних основ всередині будівель. Придатна для нанесення",
            "weight": 25,
            "price": 299.82,
            "quantity": 0,
            "totalPrice": 0
          },
          {
            "id": 13.3,
            "image": "https://i.imgur.com/EoCn52n.jpeg",
            "title": "Knauf 3000х1200х12.5 мм",
            "description": "Застосовується для виконання високоякісних штукатурних робіт на різних мінеральних основах (бетон, цегла і т.д.) усередині приміщень. Рекомендована як для традиційного ручного, так і для механічного нанесення. Після затвердіння є міцною основою для гіпсових шпаклівок і внутрішніх декоративних штукатурок.",
            "weight": 25,
            "price": 359.78,
            "quantity": 0,
            "totalPrice": 0
          }
        ]
      },
      {
        "id": 14,
        "categoryTitle": "Гіпсокартон стельовий (звичайний)",
        "isCategoryOpen": false,
        "materials": [
          {
            "id": 14.1,
            "image": "https://i.imgur.com/EoCn52n.jpeg",
            "title": "Knauf 2000х1200х9.5 мм",
            "description": "",
            "weight": 25,
            "price": 227.78,
            "quantity": 0,
            "totalPrice": 0
          },
          {
            "id": 14.2,
            "image": "https://i.imgur.com/EoCn52n.jpeg",
            "title": "Knauf 2500х1200х9.5 мм",
            "description": "Цементно-вапняна суміш з мінеральними заповнювачами та полімерними добавками.  Призначена для механізованого штукатурення всіх видів щільних мінеральних основ всередині будівель. Придатна для нанесення",
            "weight": 25,
            "price": 284.73,
            "quantity": 0,
            "totalPrice": 0
          }
        ]
      },
      {
        "id": 15,
        "categoryTitle": "Профіль для гіпсокартону CD-60",
        "isCategoryOpen": false,

        "materials": [
          {
            "id": 15.1,
            "image": "https://i.imgur.com/pZn5nEs.jpeg",
            "title": "Профіль CD-60 (0.55 мм) - 3м",
            "description": "",
            "weight": 2,
            "price": 81.9,
            "quantity": 0,
            "totalPrice": 0
          },
          {
            "id": 15.2,
            "image": "https://i.imgur.com/pZn5nEs.jpeg",
            "title": "Профіль CD-60 (0.55 мм) - 4м",
            "description": "",
            "weight": 2,
            "price": 109.2,
            "quantity": 0,
            "totalPrice": 0
          },
          {
            "id": 15.3,
            "image": "https://i.imgur.com/pZn5nEs.jpeg",
            "title": "Профіль CD-60 (0.6 мм) ГОСТ - 3м",
            "description": "",
            "weight": 2,
            "price": 105.03,
            "quantity": 0,
            "totalPrice": 0
          },
          {
            "id": 15.4,
            "image": "https://i.imgur.com/pZn5nEs.jpeg",
            "title": "Профіль CD-60 (0.6 мм) ГОСТ - 4м",
            "description": "",
            "weight": 2,
            "price": 140.04,
            "quantity": 0,
            "totalPrice": 0
          },
          {
            "id": 15.5,
            "image": "https://i.imgur.com/pZn5nEs.jpeg",
            "title": "Knauf Профіль CD-60 (0.6 мм) - 3м",
            "description": "",
            "weight": 2,
            "price": 148.23,
            "quantity": 0,
            "totalPrice": 0
          },
          {
            "id": 15.6,
            "image": "https://i.imgur.com/pZn5nEs.jpeg",
            "title": "Knauf Профіль CD-60 (0.6 мм) - 4м",
            "description": "",
            "weight": 2,
            "price": 206.2,
            "quantity": 0,
            "totalPrice": 0
          }
        ]
      },
      {
        "id": 16,
        "categoryTitle": "Профіль для гіпсокартону UD-27",
        "isCategoryOpen": false,

        "materials": [
          {
            "id": 16.1,
            "image": "https://i.imgur.com/tSzHGba.jpeg",
            "title": "Профіль UD-27 (0.55 мм) - 3м",
            "description": "",
            "weight": 2,
            "price": 50.13,
            "quantity": 0,
            "totalPrice": 0
          },
          {
            "id": 16.2,
            "image": "https://i.imgur.com/tSzHGba.jpeg",
            "title": "Профіль UD-27 (0.55 мм) - 4м",
            "description": "",
            "weight": 2,
            "price": 66.84,
            "quantity": 0,
            "totalPrice": 0
          },
          {
            "id": 16.3,
            "image": "https://i.imgur.com/tSzHGba.jpeg",
            "title": "Профіль UD-27 (0.6 мм) ГОСТ - 3м",
            "description": "",
            "weight": 2,
            "price": 65.82,
            "quantity": 0,
            "totalPrice": 0
          },
          {
            "id": 16.4,
            "image": "https://i.imgur.com/tSzHGba.jpeg",
            "title": "Профіль UD-27 (0.6 мм) ГОСТ - 4м",
            "description": "",
            "weight": 2,
            "price": 87.76,
            "quantity": 0,
            "totalPrice": 0
          },
          {
            "id": 16.5,
            "image": "https://i.imgur.com/tSzHGba.jpeg",
            "title": "Knauf Профіль UD-27 (0.6 мм) - 3м",
            "description": "",
            "weight": 2,
            "price": 106.47,
            "quantity": 0,
            "totalPrice": 0
          },
          {
            "id": 16.6,
            "image": "https://i.imgur.com/tSzHGba.jpeg",
            "title": "Knauf Профіль UD-27 (0.6 мм) - 4м",
            "description": "",
            "weight": 2,
            "price": 141.96,
            "quantity": 0,
            "totalPrice": 0
          }
        ]
      }
    ]
  }
]
